Metadata-Version: 2.1
Name: selenium-testing-module
Version: 1.0.3
Summary: A module to be used with Selenium; helps make test scripts easier to write.
Home-page: https://github.com/navaz-alani/selenium-testing-module/
Author: Navaz Alani
Author-email: nalani@uwaterloo.ca
License: MIT
Download-URL: https://github.com/navaz-alani/selenium-testing-module/archive/v1.0.2Beta.tar.gz
Keywords: testing,selenium,webdriver,automation
Platform: UNKNOWN
Classifier: Development Status :: 3 - Alpha
Classifier: Intended Audience :: Developers
Classifier: Topic :: Software Development :: Build Tools
Classifier: License :: OSI Approved :: MIT License
Classifier: Programming Language :: Python :: 3
Classifier: Programming Language :: Python :: 3.4
Classifier: Programming Language :: Python :: 3.5
Classifier: Programming Language :: Python :: 3.6
